modos/__init__.py
modos/api.py
modos/codes.py
modos/io.py
modos/logging.py
modos/prompt.py
modos/rdf.py
modos/remote.py
modos/storage.py
modos/cli/__init__.py
modos/cli/c4gh.py
modos/cli/codes.py
modos/cli/common.py
modos/cli/main.py
modos/cli/remote.py
modos/genomics/__init__.py
modos/genomics/c4gh.py
modos/genomics/cram.py
modos/genomics/formats.py
modos/genomics/htsget.py
modos/genomics/refget.py
modos/genomics/region.py
modos/helpers/__init__.py
modos/helpers/enums.py
modos/helpers/schema.py
modos/metabolomics/__init__.py
modos/metabolomics/mztab.py
modos-0.3.5.dist-info/METADATA
modos-0.3.5.dist-info/WHEEL
modos-0.3.5.dist-info/entry_points.txt
modos-0.3.5.dist-info/licenses/LICENSE
modos-0.3.5.dist-info/RECORD
