Metadata-Version: 2.4
Name: modos
Version: 0.3.5
Summary: SMOC Multi-Omics Digital Object System API
Project-URL: Homepage, https://github.com/sdsc-ordes/modos-api
Project-URL: Documentation, https://sdsc-ordes.github.io/modos-api
Project-URL: Issues, https://github.com/sdsc-ordes/modos-api/issues
Author-email: Swiss Data Science Center <contact@datascience.ch>
License: Apache-2.0
License-File: LICENSE
Requires-Python: <3.14,>=3.12
Requires-Dist: calamus<0.5.0,>=0.4.2
Requires-Dist: click<8.2.0,>=8.1.3
Requires-Dist: crypt4gh<2.0,>=1.7
Requires-Dist: gtars<0.3.0,>=0.2.2
Requires-Dist: loguru>=0.7.3
Requires-Dist: modos-schema>=0.3.4
Requires-Dist: pandas<3.0.0,>=2.2.3
Requires-Dist: platformdirs>=4.4.0
Requires-Dist: prompt-toolkit<4.0.0,>=3.0.48
Requires-Dist: pydantic<3.0.0,>=2.8.2
Requires-Dist: pyfuzon<0.5,>=0.4; sys_platform != 'win32'
Requires-Dist: pyocli<1.0.0,>=0.1.0
Requires-Dist: pysam<0.24.0,>=0.22.0
Requires-Dist: pyteomics<5.0.0,>=4.7.4
Requires-Dist: pyyaml<7.0.0,>=6.0.1
Requires-Dist: rdflib<7.0,>=6.3
Requires-Dist: s3fs<2025.0.0,>=2024.3.1
Requires-Dist: typer[rich]<1.0.0,>=0.7.0
Requires-Dist: zarr<3.0.0,>=2.16.1
